{
	"id": "60d1ed004ae32b0008dbe3e1",
	"site_id": "64f32322-7c26-4008-b886-60800cd747b0",
	"build_id": "60d1ecff4ae32b0008dbe3df",
	"state": "ready",
	"name": "material-ui",
	"url": "http://material-ui.netlify.app",
	"admin_url": "https://app.netlify.com/sites/material-ui",
	"deploy_url": "http://next--material-ui.netlify.app",
	"deploy_ssl_url": "https://next--material-ui.netlify.app",
	"created_at": "2021-06-22T14:00:32.026Z",
	"updated_at": "2021-06-22T14:21:43.529Z",
	"commit_ref": "d5a56641118a9f8d2170d6829829b10150776e12",
	"review_id": null,
	"skipped": null,
	"locked": null,
	"branch": "next",
	"commit_url": "https://github.com/mui-org/material-ui/commit/d5a56641118a9f8d2170d6829829b10150776e12",
	"log_access_attributes": {
		"type": "firebase",
		"url": "https://netlify-builds1.firebaseio.com/builds/60d1ecff4ae32b0008dbe3df/log",
		"endpoint": "https://netlify-builds1.firebaseio.com",
		"path": "/builds/60d1ecff4ae32b0008dbe3df/log",
		"token": "eyJ0eXAiOiJKV1QiLCJhbGciOiJIUzI1NiJ9.eyJ2IjowLCJpYXQiOjE2MjQzNzIyMDQsImQiOnsidWlkIjoiIn19.MAkfj1XZgDoFk3eXBIM3QxKiAZ0XnuYpUI5he9aq8zY"
	},
	"title": "[ButtonBase] Consider as a link with a custom component and `to` prop (#26576)\n\nCo-authored-by: Sebastian Silbermann <silbermann.sebastian@gmail.com>\r\nCo-authored-by: Olivier Tassinari <olivier.tassinari@gmail.com>",
	"review_url": null,
	"published_at": null,
	"context": "branch-deploy",
	"deploy_time": 794,
	"public": true,
	"plugin_state": "success"
}
